LICENSE
README.md
setup.py
pypi_package_rot/__init__.py
pypi_package_rot/__version__.py
pypi_package_rot/cli.py
pypi_package_rot.egg-info/PKG-INFO
pypi_package_rot.egg-info/SOURCES.txt
pypi_package_rot.egg-info/dependency_links.txt
pypi_package_rot.egg-info/entry_points.txt
pypi_package_rot.egg-info/requires.txt
pypi_package_rot.egg-info/top_level.txt
pypi_package_rot/api/__init__.py
pypi_package_rot/api/constants.py
pypi_package_rot/api/locally_available_packages.py
pypi_package_rot/api/project.py
pypi_package_rot/api/retrieve_all_package_names.py
pypi_package_rot/utils/__init__.py
pypi_package_rot/utils/is_valid_email.py
pypi_package_rot/utils/is_valid_url.py
tests/test_project_endpoint.py
tests/test_retrieve_all_package_names.py