Metadata-Version: 2.1
Name: pypi-package-rot
Version: 0.1.0
Summary: Tools to investigate the state of PyPI packages.
Home-page: https://github.com/LucaCappelletti94/pypi-package-rot
Author: LucaCappelletti94
License: MIT
Classifier: Development Status :: 4 - Beta
Classifier: License :: OSI Approved :: MIT License
Classifier: Programming Language :: Python :: 3
Requires-Python: >=3.9
Provides-Extra: test
License-File: LICENSE
